Workbook

Sheet Assumptions & Staffing
A1: ASSUMPTIONS & STAFFING MODEL
A3: REVENUE ASSUMPTIONS
A4: Metric | B4: Conservative | C4: Base Case | D4: Optimistic
A5: Spa - Average Treatment Price | B5: 100 | C5: 100 | D5: 100
A6: Spa - Monthly Utilization % | B6: 0.4 | C6: 0.45 | D6: 0.5
A7: Aesthetics - Average Price | B7: 250 | C7: 250 | D7: 250
A8: Spa Month 12 Revenue | B8: 30000 | C8: 40000 | D8: 50000
A9: Aesthetics Month 12 Revenue | B9: 20000 | C9: 30000 | D9: 40000
A12: STAFFING STRUCTURE
A13: Role | B13: Count | C13: Monthly Cost | D13: Notes
A14: SPA
A15: Spa Manager | B15: 1 | C15: 2500
A16: Receptionists | B16: 2 | C16: 1200 | D16: Per person
A17: Therapists | B17: 5 | C17: 1800 | D17: Per person
A19: CLINIC/AESTHETICS
A20: Medical Nurse | B20: 1 | C20: 5500
A21: Aesthetics Therapists | B21: 2 | C21: 2000 | D21: Base salary
A22: Revenue Share | D22: 5% of clinic revenue
A25: OPERATING COSTS (MONTHLY)
A26: Cost Category | B26: Amount | C26: Type | D26: Notes
A27: FACILITIES
A28: Rent | B28: 5000 | C28: Fixed
A29: Utilities | B29: 500 | C29: Fixed
A30: Maintenance & Repairs | B30: 300 | C30: Fixed
A31: Cleaning & Laundry | B31: 400 | C31: Fixed
A33: SUPPLIES
A34: Spa Consumables | B34: 3% | C34: Variable | D34: of spa revenue
A35: Aesthetic Supplies | B35: 3% | C35: Variable | D35: of aesthetic revenue
A37: MARKETING & CUSTOMER ACQUISITION
A38: Hotel Partnership Commission | B38: 5% | C38: Variable | D38: of spa revenue
A40: SYSTEMS & OPERATIONS
A41: Internet & Telephone | B41: 300 | C41: Fixed
A42: CRM/Booking System | B42: 80 | C42: Fixed
A43: Point of Sale | B43: 80 | C43: Fixed
A45: PROFESSIONAL SERVICES
A46: Accounting & Bookkeeping | B46: 400 | C46: Fixed | D46: Combined
A48: CONTINGENCY BUFFER | B48: 2% | C48: Variable | D48: of total revenue
A50: Total Fixed Costs (monthly) | B50: 7060

Sheet Monthly P&L Model
A1: 12-MONTH P&L PROJECTION (BASE CASE - WITH SEASONALITY)
A2: Month | B2: M1 | C2: M2 | D2: M3 | E2: M4 | F2: M5 | G2: M6 | H2: M7 | I2: M8 | J2: M9 | K2: M10 | L2: M11 | M2: M12
A3: REVENUE
A4: Spa Revenue | B4: 24000 | C4: 28000 | D4: 32000 | E4: 33000 | F4: 31000 | G4: 34000 | H4: 37000 | I4: 43000 | J4: 42000 | K4: 40000 | L4: 36000 | M4: 38000
A5: Aesthetics Revenue | B5: 0 | C5: 0 | D5: 10000 | E5: 15000 | F5: 18000 | G5: 20000 | H5: 21000 | I5: 23000 | J5: 24000 | K5: 25000 | L5: 27000 | M5: 30000
A6: Total Revenue | B6: =B4+B5 | C6: =C4+C5 | D6: =D4+D5 | E6: =E4+E5 | F6: =F4+F5 | G6: =G4+G5 | H6: =H4+H5 | I6: =I4+I5 | ... M6: =M4+M5
A8: OPERATING COSTS
A9: Fixed Costs | B9: 7060 | C9: 7060 | D9: 7060 | E9: 7060 | F9: 7060 | G9: 7060 | H9: 7060 | I9: 7060 | J9: 7060 | K9: 7060 | L9: 7060 | M9: 7060
A10: Spa Consumables (3%) | B10: =B4*0.03 | C10: =C4*0.03 | D10: =D4*0.03 | E10: =E4*0.03 | F10: =F4*0.03 | G10: =G4*0.03 | H10: =H4*0.03 | I10: =I4*0.03 | ... M10: =M4*0.03
A11: Aesthetic Supplies (3%) | B11: =B5*0.03 | C11: =C5*0.03 | D11: =D5*0.03 | E11: =E5*0.03 | F11: =F5*0.03 | G11: =G5*0.03 | H11: =H5*0.03 | I11: =I5*0.03 | ... M11: =M5*0.03
A12: Hotel Partnership (5% Spa) | B12: =B4*0.05 | C12: =C4*0.05 | D12: =D4*0.05 | E12: =E4*0.05 | F12: =F4*0.05 | G12: =G4*0.05 | H12: =H4*0.05 | I12: =I4*0.05 | ... M12: =M4*0.05
A13: Contingency (2% Total) | B13: =B6*0.02 | C13: =C6*0.02 | D13: =D6*0.02 | E13: =E6*0.02 | F13: =F6*0.02 | G13: =G6*0.02 | H13: =H6*0.02 | I13: =I6*0.02 | ... M13: =M6*0.02
A14: Total Variable Costs | B14: =B10+B11+B12+B13 | C14: =C10+C11+C12+C13 | D14: =D10+D11+D12+D13 | E14: =E10+E11+E12+E13 | F14: =F10+F11+F12+F13 | G14: =G10+G11+G12+G13 | H14: =H10+H11+H12+H13 | I14: =I10+I11+I12+I13 | ... M14: =M10+M11+M12+M13
A15: TOTAL OPERATING COSTS | B15: =B9+B14 | C15: =C9+C14 | D15: =D9+D14 | E15: =E9+E14 | F15: =F9+F14 | G15: =G9+G14 | H15: =H9+H14 | I15: =I9+I14 | ... M15: =M9+M14
A17: PAYROLL
A18: Spa Payroll | B18: 13900 | C18: 13900 | D18: 13900 | E18: 13900 | F18: 13900 | G18: 13900 | H18: 13900 | I18: 13900 | J18: 13900 | K18: 13900 | L18: 13900 | M18: 13900
A19: Clinic Base Payroll | B19: 9500 | C19: 9500 | D19: 9500 | E19: 9500 | F19: 9500 | G19: 9500 | H19: 9500 | I19: 9500 | J19: 9500 | K19: 9500 | L19: 9500 | M19: 9500
A20: Clinic Revenue Share (5%) | B20: =B5*0.05 | C20: =C5*0.05 | D20: =D5*0.05 | E20: =E5*0.05 | F20: =F5*0.05 | G20: =G5*0.05 | H20: =H5*0.05 | I20: =I5*0.05 | ... M20: =M5*0.05
A21: TOTAL PAYROLL | B21: =B18+B19+B20 | C21: =C18+C19+C20 | D21: =D18+D19+D20 | E21: =E18+E19+E20 | F21: =F18+F19+F20 | G21: =G18+G19+G20 | H21: =H18+H19+H20 | I21: =I18+I19+I20 | ... M21: =M18+M19+M20
A23: EBITDA | B23: =B6-B15-B21 | C23: =C6-C15-C21 | D23: =D6-D15-D21 | E23: =E6-E15-E21 | F23: =F6-F15-F21 | G23: =G6-G15-G21 | H23: =H6-H15-H21 | I23: =I6-I15-I21 | ... M23: =M6-M15-M21

Sheet Annual Summary & KPIs
A1: ANNUAL SUMMARY & KPIs (YEAR 1 - BASE CASE)
A3: REVENUE SUMMARY
A4: Spa Revenue (Year 1) | B4: =SUM('Monthly P&L Model'!B4:M4)
A5: Aesthetics Revenue (Year 1) | B5: =SUM('Monthly P&L Model'!B5:M5)
A6: Total Revenue (Year 1) | B6: =SUM('Monthly P&L Model'!B6:M6)
A8: OPERATING SUMMARY
A9: Total Operating Costs | B9: =SUM('Monthly P&L Model'!B15:M15)
A10: Total Payroll | B10: =SUM('Monthly P&L Model'!B21:M21)
A11: Year 1 EBITDA | B11: =SUM('Monthly P&L Model'!B23:M23)
A13: KEY PERFORMANCE INDICATORS
A14: EBITDA Margin | B14: =B11/B6
A15: Payroll % of Revenue | B15: =B10/B6
A16: OpEx % of Revenue | B16: =B9/B6
A18: Payroll Breakdown
A19: Spa Payroll (Annual) | B19: =SUM('Monthly P&L Model'!B18:M18)
A20: Clinic Base (Annual) | B20: =SUM('Monthly P&L Model'!B19:M19)
A21: Revenue Share (Annual) | B21: =SUM('Monthly P&L Model'!B20:M20)
